brookesia/Class_def.py
brookesia/Computation.py
brookesia/DRG.py
brookesia/GUI_red_mech.py
brookesia/GeneralFunctions.py
brookesia/GeneticAlgorithm.py
brookesia/PSO.py
brookesia/SA.py
brookesia/TSA.py
brookesia/__init__.py
brookesia/_toolbox_Plot_fitness.py
brookesia/_toolbox_Plot_species.py
brookesia/ign_delay_sens.py
brookesia/wd_manage_gui.py
brookesia/wd_select_gui.py
brookesia/write_conditions_input.py
brookesia/write_kinetic_mech.py
brookesia/write_results_input.py
brookesia-1.8.4.dist-info/LICENSE
brookesia-1.8.4.dist-info/METADATA
brookesia-1.8.4.dist-info/WHEEL
brookesia-1.8.4.dist-info/top_level.txt
brookesia-1.8.4.dist-info/RECORD
