Metadata-Version: 2.1
Name: brookesia
Version: 1.8.4
Summary: Brookesia is a python-based program dedicated to the reduction ad the optimization of kinetic mechanisms.
Home-page: https://github.com/Brookesia-py/Brookesia
Author: Alexis Matynia
Author-email: alexis.matynia@sorbonne-universite.fr
Classifier: Programming Language :: Python :: 3
Classifier: License :: OSI Approved :: GNU General Public License v3 (GPLv3)
Classifier: Operating System :: OS Independent
Requires-Python: >=3.6
License-File: LICENSE
